lektor_disqus_comments.py
lektor_disqus_comments-0.4.1.dist-info/LICENSE
lektor_disqus_comments-0.4.1.dist-info/METADATA
lektor_disqus_comments-0.4.1.dist-info/WHEEL
lektor_disqus_comments-0.4.1.dist-info/entry_points.txt
lektor_disqus_comments-0.4.1.dist-info/top_level.txt
lektor_disqus_comments-0.4.1.dist-info/RECORD
