Metadata-Version: 2.1
Name: lektor-disqus-comments
Version: 0.4.1
Summary: Lektor plugin to add Disqus comments to a website.
Home-page: http://github.com/lektor/lektor-disqus-comments
Author: Armin Ronacher
Author-email: armin.ronacher@active-4.com
License: BSD
Keywords: Lektor plugin static-site blog Disqus comments
Platform: UNKNOWN
Classifier: Environment :: Plugins
Classifier: Environment :: Web Environment
Classifier: Framework :: Lektor
Classifier: Intended Audience :: Developers
Classifier: License :: OSI Approved :: BSD License
